eesrep/__init__.py
eesrep/eesrep_enum.py
eesrep/eesrep_exceptions.py
eesrep/eesrep_io.py
eesrep/main.py
eesrep/test_interface_solver.py
eesrep/components/__init__.py
eesrep/components/bus.py
eesrep/components/converter.py
eesrep/components/dam.py
eesrep/components/generic_component.py
eesrep/components/sink_source.py
eesrep/components/storage.py
eesrep/components/tool.py
eesrep/solver_interface/__init__.py
eesrep/solver_interface/docplex_interface.py
eesrep/solver_interface/generic_interface.py
eesrep/solver_interface/interface_tester.py
eesrep/solver_interface/mip_interface.py
eesrep/solver_interface/pyomo_interface.py
eesrep-0.1.5.dist-info/LICENSE
eesrep-0.1.5.dist-info/METADATA
eesrep-0.1.5.dist-info/WHEEL
eesrep-0.1.5.dist-info/top_level.txt
eesrep-0.1.5.dist-info/RECORD
